pybuilder_radon/__init__.py
pybuilder_radon/task.py
pybuilder_radon-0.3.3.dist-info/METADATA
pybuilder_radon-0.3.3.dist-info/WHEEL
pybuilder_radon-0.3.3.dist-info/namespace_packages.txt
pybuilder_radon-0.3.3.dist-info/top_level.txt
pybuilder_radon-0.3.3.dist-info/zip-safe
pybuilder_radon-0.3.3.dist-info/RECORD
