Metadata-Version: 2.1
Name: pybuilder-radon
Version: 0.3.3
Summary: Pybuilder plugin for radon cyclomatic complexity
Home-page: https://github.com/soda480/pybuilder-radon
Author: Emilio Reyes
Author-email: soda480@gmail.com
Maintainer: 
Maintainer-email: 
License: Apache License, Version 2.0
Classifier: Development Status :: 4 - Beta
Classifier: Environment :: Other Environment
Classifier: Environment :: Plugins
Classifier: Intended Audience :: Developers
Classifier: Intended Audience :: System Administrators
Classifier: License :: OSI Approved :: Apache Software License
Classifier: Operating System :: POSIX :: Linux
Classifier: Programming Language :: Python
Classifier: Programming Language :: Python :: 3.7
Classifier: Programming Language :: Python :: 3.8
Classifier: Programming Language :: Python :: 3.9
Classifier: Programming Language :: Python :: 3.10
Classifier: Topic :: Software Development :: Build Tools
Requires-Dist: radon
